odoo/addons/stock_quant_package_dimension/README.rst
odoo/addons/stock_quant_package_dimension/__init__.py
odoo/addons/stock_quant_package_dimension/__manifest__.py
odoo/addons/stock_quant_package_dimension/i18n/stock_quant_package_dimension.pot
odoo/addons/stock_quant_package_dimension/models/__init__.py
odoo/addons/stock_quant_package_dimension/models/stock_quant_package.py
odoo/addons/stock_quant_package_dimension/readme/CONTRIBUTORS.rst
odoo/addons/stock_quant_package_dimension/readme/DESCRIPTION.rst
odoo/addons/stock_quant_package_dimension/static/description/icon.png
odoo/addons/stock_quant_package_dimension/static/description/index.html
odoo/addons/stock_quant_package_dimension/tests/__init__.py
odoo/addons/stock_quant_package_dimension/tests/common.py
odoo/addons/stock_quant_package_dimension/tests/test_package_dimension.py
odoo/addons/stock_quant_package_dimension/views/stock_quant_package.xml
odoo13_addon_stock_quant_package_dimension-13.0.1.1.0.dist-info/METADATA
odoo13_addon_stock_quant_package_dimension-13.0.1.1.0.dist-info/WHEEL
odoo13_addon_stock_quant_package_dimension-13.0.1.1.0.dist-info/top_level.txt
odoo13_addon_stock_quant_package_dimension-13.0.1.1.0.dist-info/RECORD
